pistatus/__init__.py
pistatus/__main__.py
pistatus/static/style.css
pistatus/templates/index.html
pistatus-1.0.0.1.dist-info/LICENSE
pistatus-1.0.0.1.dist-info/METADATA
pistatus-1.0.0.1.dist-info/WHEEL
pistatus-1.0.0.1.dist-info/entry_points.txt
pistatus-1.0.0.1.dist-info/top_level.txt
pistatus-1.0.0.1.dist-info/RECORD
