Metadata-Version: 2.1
Name: pistatus
Version: 1.0.0.1
Summary: An application that allows you to check the status of your Raspberry Pi
Home-page: UNKNOWN
Author: Sam Poder
Author-email: 23samuel.p@gwa.edu.sg
License: UNKNOWN
Platform: UNKNOWN
Classifier: Programming Language :: Python
Classifier: License :: OSI Approved :: MIT License
Requires-Python: >=3.6
Requires-Dist: psutil
